modernbert_doc_cls/__init__.py
modernbert_doc_cls/cli.py
modernbert_doc_cls/inference.py
modernbert_doc_cls/data/extraction.py
modernbert_doc_cls/training/train.py
modernbert_doc_cls-0.1.0.dist-info/licenses/LICENSE
modernbert_doc_cls-0.1.0.dist-info/METADATA
modernbert_doc_cls-0.1.0.dist-info/WHEEL
modernbert_doc_cls-0.1.0.dist-info/entry_points.txt
modernbert_doc_cls-0.1.0.dist-info/top_level.txt
modernbert_doc_cls-0.1.0.dist-info/RECORD
