Metadata-Version: 2.4
Name: modernbert-doc-cls
Version: 0.1.0
Summary: A document classification library using ModernBERT
Author-email: Pavan Yadav <yadavpavankrr@gmail.com>
Classifier: Programming Language :: Python :: 3
Classifier: License :: OSI Approved :: MIT License
Classifier: Operating System :: OS Independent
Requires-Python: >=3.8
License-File: LICENSE
Requires-Dist: torch
Requires-Dist: transformers
Requires-Dist: datasets
Requires-Dist: pandas
Requires-Dist: scikit-learn
Requires-Dist: matplotlib
Requires-Dist: seaborn
Requires-Dist: pyyaml
Requires-Dist: langchain
Requires-Dist: langchain-community
Requires-Dist: docling
Requires-Dist: langchain-docling
Dynamic: license-file
